Heteogeneous_Highway_Env/__init__.py
Heteogeneous_Highway_Env/interval.py
Heteogeneous_Highway_Env/utils.py
Heteogeneous_Highway_Env/envs/__init__.py
Heteogeneous_Highway_Env/envs/exit_env.py
Heteogeneous_Highway_Env/envs/highway_env.py
Heteogeneous_Highway_Env/envs/intersection_env.py
Heteogeneous_Highway_Env/envs/lane_keeping_env.py
Heteogeneous_Highway_Env/envs/merge_env.py
Heteogeneous_Highway_Env/envs/parking_env.py
Heteogeneous_Highway_Env/envs/racetrack_env.py
Heteogeneous_Highway_Env/envs/roundabout_env.py
Heteogeneous_Highway_Env/envs/summon_env.py
Heteogeneous_Highway_Env/envs/two_way_env.py
Heteogeneous_Highway_Env/envs/u_turn_env.py
Heteogeneous_Highway_Env/envs/common/__init__.py
Heteogeneous_Highway_Env/envs/common/abstract.py
Heteogeneous_Highway_Env/envs/common/action.py
Heteogeneous_Highway_Env/envs/common/finite_mdp.py
Heteogeneous_Highway_Env/envs/common/graphics.py
Heteogeneous_Highway_Env/envs/common/observation.py
Heteogeneous_Highway_Env/road/__init__.py
Heteogeneous_Highway_Env/road/graphics.py
Heteogeneous_Highway_Env/road/lane.py
Heteogeneous_Highway_Env/road/regulation.py
Heteogeneous_Highway_Env/road/road.py
Heteogeneous_Highway_Env/road/spline.py
Heteogeneous_Highway_Env/vehicle/__init__.py
Heteogeneous_Highway_Env/vehicle/behavior.py
Heteogeneous_Highway_Env/vehicle/controller.py
Heteogeneous_Highway_Env/vehicle/dynamics.py
Heteogeneous_Highway_Env/vehicle/graphics.py
Heteogeneous_Highway_Env/vehicle/kinematics.py
Heteogeneous_Highway_Env/vehicle/objects.py
Heteogeneous_Highway_Env/vehicle/uncertainty/__init__.py
Heteogeneous_Highway_Env/vehicle/uncertainty/estimation.py
Heteogeneous_Highway_Env/vehicle/uncertainty/prediction.py
Heterogeneous_Highway_Env/__init__.py
Heterogeneous_Highway_Env/interval.py
Heterogeneous_Highway_Env/utils.py
Heterogeneous_Highway_Env/envs/__init__.py
Heterogeneous_Highway_Env/envs/exit_env.py
Heterogeneous_Highway_Env/envs/highway_env.py
Heterogeneous_Highway_Env/envs/intersection_env.py
Heterogeneous_Highway_Env-0.0.3.dist-info/LICENSE
Heterogeneous_Highway_Env-0.0.3.dist-info/METADATA
Heterogeneous_Highway_Env-0.0.3.dist-info/WHEEL
Heterogeneous_Highway_Env-0.0.3.dist-info/top_level.txt
Heterogeneous_Highway_Env-0.0.3.dist-info/RECORD
