Metadata-Version: 2.1
Name: Heterogeneous_Highway_Env
Version: 0.0.3
Summary: Codebase for for our version of highway-way modified for iPLAN paper
Home-page: https://github.com/wuxiyang1996/Heterogeneous_Highway_Env
Author: Xiyang Wu
Author-email: wuxiyang1996@gmail.com
Classifier: Programming Language :: Python :: 3
Classifier: License :: OSI Approved :: MIT License
Classifier: Operating System :: OS Independent
License-File: LICENSE
